{
    "home-manager": {
        "branch": "master",
        "description": "Manage a user environment using Nix  [maintainer=@rycee] ",
        "homepage": "https://nix-community.github.io/home-manager/",
        "owner": "nix-community",
        "repo": "home-manager",
        "rev": "c491331718bd41722a2982a5532eb0ff51c3ca28",
        "sha256": "0nirmf81l5iqwrdrdjx6kzp2pkbqrcml0gq41infi8nf633pgghd",
        "type": "tarball",
        "url": "https://github.com/nix-community/home-manager/archive/c491331718bd41722a2982a5532eb0ff51c3ca28.tar.gz",
        "url_template": "https://github.com/<owner>/<repo>/archive/<rev>.tar.gz"
    },
    "neovim": {
        "branch": "master",
        "description": "Vim-fork focused on extensibility and usability",
        "homepage": "https://neovim.io",
        "owner": "neovim",
        "repo": "neovim",
        "rev": "de6f9233eee937139f607d3a59fd5b1f479d8a13",
        "sha256": "0k487lzgm8yk4j2pxb7iv54xv812bg1a3jjfgc7cwq8pag4cr0a6",
        "type": "tarball",
        "url": "https://github.com/neovim/neovim/archive/de6f9233eee937139f607d3a59fd5b1f479d8a13.tar.gz",
        "url_template": "https://github.com/<owner>/<repo>/archive/<rev>.tar.gz"
    },
    "niv": {
        "branch": "master",
        "description": "Easy dependency management for Nix projects",
        "homepage": "https://github.com/nmattia/niv",
        "owner": "nmattia",
        "repo": "niv",
        "rev": "5830a4dd348d77e39a0f3c4c762ff2663b602d4c",
        "sha256": "1d3lsrqvci4qz2hwjrcnd8h5vfkg8aypq3sjd4g3izbc8frwz5sm",
        "type": "tarball",
        "url": "https://github.com/nmattia/niv/archive/5830a4dd348d77e39a0f3c4c762ff2663b602d4c.tar.gz",
        "url_template": "https://github.com/<owner>/<repo>/archive/<rev>.tar.gz"
    },
    "nixpkgs": {
        "branch": "master",
        "description": "Nix Packages collection",
        "homepage": null,
        "owner": "NixOS",
        "repo": "nixpkgs",
        "rev": "7db33b1849b5074a51d81f692fe27842cc6d1c90",
        "sha256": "04jv5sn7m9lkyglsxvsj812inwzniw8ghvd09lmvyjjxqykajq17",
        "type": "tarball",
        "url": "https://github.com/NixOS/nixpkgs/archive/7db33b1849b5074a51d81f692fe27842cc6d1c90.tar.gz",
        "url_template": "https://github.com/<owner>/<repo>/archive/<rev>.tar.gz"
    }
}
