{
    "home-manager": {
        "branch": "master",
        "description": "Manage a user environment using Nix  [maintainer=@rycee] ",
        "homepage": "https://nix-community.github.io/home-manager/",
        "owner": "nix-community",
        "repo": "home-manager",
        "rev": "06ee8ec8dfc4554c374052cd7b7083765748af99",
        "sha256": "1g2d6f4mhj71drnyh8wa7358f36vfw7yxdfq9cjwff1zaa9lp142",
        "type": "tarball",
        "url": "https://github.com/nix-community/home-manager/archive/06ee8ec8dfc4554c374052cd7b7083765748af99.tar.gz",
        "url_template": "https://github.com/<owner>/<repo>/archive/<rev>.tar.gz"
    },
    "neovim": {
        "branch": "master",
        "description": "Vim-fork focused on extensibility and usability",
        "homepage": "https://neovim.io",
        "owner": "neovim",
        "repo": "neovim",
        "rev": "e2bc7e321b4a8bec3727cf342a84eb1e85dadbc8",
        "sha256": "1rn4dz8hyhqklbl5qw56yhl4kcm9g5lh452d6bsxbj0n0yk964rr",
        "type": "tarball",
        "url": "https://github.com/neovim/neovim/archive/e2bc7e321b4a8bec3727cf342a84eb1e85dadbc8.tar.gz",
        "url_template": "https://github.com/<owner>/<repo>/archive/<rev>.tar.gz"
    },
    "niv": {
        "branch": "master",
        "description": "Easy dependency management for Nix projects",
        "homepage": "https://github.com/nmattia/niv",
        "owner": "nmattia",
        "repo": "niv",
        "rev": "e0ca65c81a2d7a4d82a189f1e23a48d59ad42070",
        "sha256": "1pq9nh1d8nn3xvbdny8fafzw87mj7gsmp6pxkdl65w2g18rmcmzx",
        "type": "tarball",
        "url": "https://github.com/nmattia/niv/archive/e0ca65c81a2d7a4d82a189f1e23a48d59ad42070.tar.gz",
        "url_template": "https://github.com/<owner>/<repo>/archive/<rev>.tar.gz"
    },
    "nixpkgs": {
        "branch": "master",
        "description": "Nix Packages collection",
        "homepage": null,
        "owner": "NixOS",
        "repo": "nixpkgs",
        "rev": "2d8e3aa2885dfce613e70ee756b8cd2ed0c23aec",
        "sha256": "086xk0cbq7nzypdyshr1fikbrkwfj5bnppbwibv3avkjkrfyba5w",
        "type": "tarball",
        "url": "https://github.com/NixOS/nixpkgs/archive/2d8e3aa2885dfce613e70ee756b8cd2ed0c23aec.tar.gz",
        "url_template": "https://github.com/<owner>/<repo>/archive/<rev>.tar.gz"
    }
}
